tests/__init__.py
tests/test_doctests.py
tests/test_trendypy.py
trendypy/__init__.py
trendypy/algos.py
trendypy/trendy.py
trendypy/utils.py
trendypy-0.2.2.dist-info/LICENSE
trendypy-0.2.2.dist-info/METADATA
trendypy-0.2.2.dist-info/WHEEL
trendypy-0.2.2.dist-info/top_level.txt
trendypy-0.2.2.dist-info/RECORD
