Metadata-Version: 2.1
Name: trendypy
Version: 0.2.2
Summary: A package for trend line clustering.
Home-page: https://github.com/ddaskan/trendypy
Author: Dogan Askan
Author-email: doganaskan@gmail.com
License: MIT
Download-URL: https://pypi.python.org/pypi/trendypy
Project-URL: Bug Tracker, https://github.com/ddaskan/trendypy/issues
Project-URL: Documentation, https://trendypy.readthedocs.io/
Project-URL: Source Code, https://github.com/ddaskan/trendypy
Keywords: ml ai data-analysis machine-learning clustering
Platform: UNKNOWN
Classifier: Programming Language :: Python :: 3
Classifier: License :: OSI Approved :: MIT License
Classifier: Operating System :: OS Independent
Classifier: Topic :: Scientific/Engineering
Classifier: Topic :: Scientific/Engineering :: Artificial Intelligence
Classifier: Topic :: Software Development
Requires-Python: >=3.7
Requires-Dist: numpy (>=1.20.2)
Requires-Dist: pandas (>=1.2.4)
Requires-Dist: fastdtw (>=0.3.4)
